libpardus/__init__.py
libpardus/Ptk/AboutWindow.py
libpardus/Ptk/App.py
libpardus/Ptk/ApplicationWindow.py
libpardus/Ptk/Box.py
libpardus/Ptk/Button.py
libpardus/Ptk/Flowbox.py
libpardus/Ptk/Image.py
libpardus/Ptk/Label.py
libpardus/Ptk/ListBox.py
libpardus/Ptk/ListBoxRow.py
libpardus/Ptk/Scale.py
libpardus/Ptk/ScrolledWindow.py
libpardus/Ptk/Separator.py
libpardus/Ptk/Stack.py
libpardus/Ptk/ToggleButton.py
libpardus/Ptk/Widget.py
libpardus/Ptk/gtk_settings.py
libpardus/Ptk/utils.py
libpardus-0.0.1.dist-info/METADATA
libpardus-0.0.1.dist-info/WHEEL
libpardus-0.0.1.dist-info/top_level.txt
libpardus-0.0.1.dist-info/RECORD
